safetykit/__init__.py
safetykit/_base_client.py
safetykit/_client.py
safetykit/_compat.py
safetykit/_constants.py
safetykit/_exceptions.py
safetykit/_files.py
safetykit/_models.py
safetykit/_qs.py
safetykit/_resource.py
safetykit/_response.py
safetykit/_streaming.py
safetykit/_types.py
safetykit/_version.py
safetykit/py.typed
safetykit/_utils/__init__.py
safetykit/_utils/_compat.py
safetykit/_utils/_datetime_parse.py
safetykit/_utils/_logs.py
safetykit/_utils/_proxy.py
safetykit/_utils/_reflection.py
safetykit/_utils/_resources_proxy.py
safetykit/_utils/_streams.py
safetykit/_utils/_sync.py
safetykit/_utils/_transform.py
safetykit/_utils/_typing.py
safetykit/_utils/_utils.py
safetykit/lib/.keep
safetykit/resources/__init__.py
safetykit/resources/batches.py
safetykit/resources/data.py
safetykit/resources/decisions.py
safetykit/types/__init__.py
safetykit/types/batch_create_params.py
safetykit/types/batch_create_response.py
safetykit/types/batch_get_response.py
safetykit/types/data_add_params.py
safetykit/types/data_add_response.py
safetykit/types/data_get_status_response.py
safetykit/types/decision_create_params.py
safetykit/types/decision_create_response.py
safetykit/types/decision_get_response.py
safetykit-0.3.0a0.dist-info/METADATA
safetykit-0.3.0a0.dist-info/WHEEL
safetykit-0.3.0a0.dist-info/licenses/LICENSE
safetykit-0.3.0a0.dist-info/RECORD
